README.md
setup.py
pulumi_tls_self_signed_cert/__init__.py
pulumi_tls_self_signed_cert/_enums.py
pulumi_tls_self_signed_cert/_utilities.py
pulumi_tls_self_signed_cert/provider.py
pulumi_tls_self_signed_cert/pulumi-plugin.json
pulumi_tls_self_signed_cert/py.typed
pulumi_tls_self_signed_cert/self_signed_certificate.py
pulumi_tls_self_signed_cert.egg-info/PKG-INFO
pulumi_tls_self_signed_cert.egg-info/SOURCES.txt
pulumi_tls_self_signed_cert.egg-info/dependency_links.txt
pulumi_tls_self_signed_cert.egg-info/not-zip-safe
pulumi_tls_self_signed_cert.egg-info/requires.txt
pulumi_tls_self_signed_cert.egg-info/top_level.txt