Metadata-Version: 2.1
Name: pulumi-tls-self-signed-cert
Version: 0.1.3
Summary: UNKNOWN
Home-page: UNKNOWN
License: UNKNOWN
Platform: UNKNOWN
